{"artist":"DECO*27","designer":"Radiumerst","difficulty":"MASTER","diffNum":4,"level":null,"timingList":[{"currentBpm":194.0,"havePlayed":false,"HSpeed":1.0,"noteList":[{"holdTime":0.0,"isBreak":false,"isEx":false,"isFakeRotate":false,"isForceStar":false,"isHanabi":false,"isSlideBreak":false,"isSlideNoHead":false,"noteContent":"1","noteType":0,"slideStartTime":0.0,"slideTime":0.0,"startPosition":1,"touchArea":" "},{"holdTime":0.0,"isBreak":false,"isEx":false,"isFakeRotate":false,"isForceStar":false,"isHanabi":false,"isSlideBreak":false,"isSlideNoHead":false,"noteContent":"2","noteType":0,"slideStartTime":0.0,"slideTime":0.0,"startPosition":2,"touchArea":" "}],"notesContent":"1/2","rawTextPositionX":13,"rawTextPositionY":0,"time":3.2092784458828953},{"currentBpm":194.0,"havePlayed":false,"HSpeed":1.0,"noteList":[{"holdTime":0.0,"isBreak":false,"isEx":false,"isFakeRotate":false,"isForceStar":false,"isHanabi":false,"isSlideBreak":false,"isSlideNoHead":false,"noteContent":"3","noteType":0,"slideStartTime":0.0,"slideTime":0.0,"startPosition":3,"touchArea":" "},{"holdTime":0.0,"isBreak":false,"isEx":false,"isFakeRotate":false,"isForceStar":false,"isHanabi":false,"isSlideBreak":false,"isSlideNoHead":false,"noteContent":"8","noteType":0,"slideStartTime":0.0,"slideTime":0.0,"startPosition":8,"touchArea":" "}],"notesContent":"3/8","rawTextPositionX":17,"rawTextPositionY":0,"time":3.518556796398359},{"currentBpm":194.0,"havePlayed":false,"HSpeed":1.0,"noteList":[{"holdTime":0.0,"isBreak":false,"isEx":false,"isFakeRotate":false,"isForceStar":false,"isHanabi":false,"isSlideBreak":false,"isSlideNoHead":false,"noteContent":"4","noteType":0,"slideStartTime":0.0,"slideTime":0.0,"startPosition":4,"touchArea":" "},{"holdTime":0.0,"isBreak":false,"isEx":false,"isFakeRotate":false,"isForceStar":false,"isHanabi":false,"isSlideBreak":false,"isSlideNoHead":false,"noteContent":"7","noteType":0,"slideStartTime":0.0,"slideTime":0.0,"startPosition":7,"touchArea":" "}],"notesContent":"4/7","rawTextPositionX":21,"rawTextPositionY":0,"time":3.8278351469138228},{"currentBpm":194.0,"havePlayed":false,"HSpeed":1.0,"noteList":[{"holdTime":0.0,"isBreak":false,"isEx":false,"isFakeRotate":false,"isForceStar":false,"isHanabi":false,"isSlideBreak":false,"isSlideNoHead":false,"noteContent":"5","noteType":0,"slideStartTime":0.0,"slideTime":0.0,"startPosition":5,"touchArea":" "},{"holdTime":0.6185567010309279,"isBreak":false,"isEx":false,"isFakeRotate":false,"isForceStar":false,"isHanabi":false,"isSlideBreak":false,"isSlideNoHead":false,"noteContent":"6h[2:1]","noteType":2,"slideStartTime":0.0,"slideTime":0.0,"startPosition":6,"touchArea":" "}],"notesContent":"5/6h[2:1]","rawTextPositionX":31,"rawTextPositionY":0,"time":4.1371134974292865},{"currentBpm":194.0,"havePlayed":false,"HSpeed":1.0,"noteList":[{"holdTime":0.5412371134020619,"isBreak":false,"isEx":false,"isFakeRotate":false,"isForceStar":false,"isHanabi":false,"isSlideBreak":false,"isSlideNoHead":false,"noteContent":"5h[16:7]","noteType":2,"slideStartTime":0.0,"slideTime":0.0,"startPosition":5,"touchArea":" "}],"notesContent":"5h[16:7]","rawTextPositionX":41,"rawTextPositionY":0,"time":4.755670198460214},{"currentBpm":194.0,"havePlayed":false,"HSpeed":1.0,"noteList":[{"holdTime":0.6185567010309279,"isBreak":false,"isEx":false,"isFakeRotate":false,"isForceStar":false,"isHanabi":false,"isSlideBreak":false,"isSlideNoHead":false,"noteContent":"4h[2:1]","noteType":2,"slideStartTime":0.0,"slideTime":0.0,"startPosition":4,"touchArea":" "}],"notesContent":"4h[2:1]","rawTextPositionX":50,"rawTextPositionY":0,"time":5.374226899491141},{"currentBpm":194.0,"havePlayed":false,"HSpeed":1.0,"noteList":[{"holdTime":0.6185567010309279,"isBreak":false,"isEx":false,"isFakeRotate":false,"isForceStar":false,"isHanabi":false,"isSlideBreak":false,"isSlideNoHead":false,"noteContent":"3h[2:1]","noteType":2,"slideStartTime":0.0,"slideTime":0.0,"startPosition":3,"touchArea":" "}],"notesContent":"3h[2:1]","rawTextPositionX":59,"rawTextPositionY":0,"time":5.992783600522069},{"currentBpm":194.0,"havePlayed":false,"HSpeed":1.0,"noteList":[{"holdTime":0.0,"isBreak":false,"isEx":false,"isFakeRotate":false,"isForceStar":false,"isHanabi":false,"isSlideBreak":false,"isSlideNoHead":false,"noteContent":"2","noteType":0,"slideStartTime":0.0,"slideTime":0.0,"startPosition":2,"touchArea":" "},{"holdTime":0.0,"isBreak":false,"isEx":false,"isFakeRotate":false,"isForceStar":false,"isHanabi":false,"isSlideBreak":false,"isSlideNoHead":false,"noteContent":"6","noteType":0,"slideStartTime":0.0,"slideTime":0.0,"startPosition":6,"touchArea":" "}],"notesContent":"2/6","rawTextPositionX":64,"rawTextPositionY":0,"time":6.611340301552996},{"currentBpm":194.0,"havePlayed":false,"HSpeed":1.0,"noteList":[{"holdTime":0.0,"isBreak":false,"isEx":false,"isFakeRotate":false,"isForceStar":false,"isHanabi":false,"isSlideBreak":false,"isSlideNoHead":false,"noteContent":"3","noteType":0,"slideStartTime":0.0,"slideTime":0.0,"startPosition":3,"touchArea":" "},{"holdTime":0.0,"isBreak":false,"isEx":false,"isFakeRotate":false,"isForceStar":false,"isHanabi":false,"isSlideBreak":false,"isSlideNoHead":false,"noteContent":"7","noteType":0,"slideStartTime":0.0,"slideTime":0.0,"startPosition":7,"touchArea":" "}],"notesContent":"3/7","rawTextPositionX":68,"rawTextPositionY":0,"time":6.92061865206846},{"currentBpm":194.0,"havePlayed":false,"HSpeed":1.0,"noteList":[{"holdTime":0.0,"isBreak":false,"isEx":false,"isFakeRotate":false,"isForceStar":false,"isHanabi":false,"isSlideBreak":false,"isSlideNoHead":false,"noteContent":"4","noteType":0,"slideStartTime":0.0,"slideTime":0.0,"startPosition":4,"touchArea":" "},{"holdTime":0.0,"isBreak":false,"isEx":false,"isFakeRotate":false,"isForceStar":false,"isHanabi":false,"isSlideBreak":false,"isSlideNoHead":false,"noteContent":"8","noteType":0,"slideStartTime":0.0,"slideTime":0.0,"startPosition":8,"touchArea":" "}],"notesContent":"4/8","rawTextPositionX":72,"rawTextPositionY":0,"time":7.2298970025839235},{"currentBpm":194.0,"havePlayed":false,"HSpeed":1.0,"noteList":[{"holdTime":0.0,"isBreak":false,"isEx":false,"isFakeRotate":false,"isForceStar":false,"isHanabi":false,"isSlideBreak":false,"isSlideNoHead":false,"noteContent":"1","noteType":0,"slideStartTime":0.0,"slideTime":0.0,"startPosition":1,"touchArea":" "},{"holdTime":0.0,"isBreak":false,"isEx":false,"isFakeRotate":false,"isForceStar":false,"isHanabi":false,"isSlideBreak":false,"isSlideNoHead":false,"noteContent":"5","noteType":0,"slideStartTime":0.0,"slideTime":0.0,"startPosition":5,"touchArea":" "}],"notesContent":"1/5","rawTextPositionX":76,"rawTextPositionY":0,"time":7.539175353099387},{"currentBpm":194.0,"havePlayed":false,"HSpeed":1.0,"noteList":[{"holdTime":0.0,"isBreak":false,"isEx":false,"isFakeRotate":false,"isForceStar":false,"isHanabi":false,"isSlideBreak":false,"isSlideNoHead":false,"noteContent":"7","noteType":0,"slideStartTime":0.0,"slideTime":0.0,"startPosition":7,"touchArea":" "},{"holdTime":0.0,"isBreak":false,"isEx":false,"isFakeRotate":false,"isForceStar":false,"isHanabi":false,"isSlideBreak":false,"isSlideNoHead":false,"noteContent":"8","noteType":0,"slideStartTime":0.0,"slideTime":0.0,"startPosition":8,"touchArea":" "}],"notesContent":"7/8","rawTextPositionX":5,"rawTextPositionY":1,"time":8.157732054130316},{"currentBpm":194.0,"havePlayed":false,"HSpeed":1.0,"noteList":[{"holdTime":0.0,"isBreak":false,"isEx":false,"isFakeRotate":false,"isForceStar":false,"isHanabi":false,"isSlideBreak":false,"isSlideNoHead":false,"noteContent":"1","noteType":0,"slideStartTime":0.0,"slideTime":0.0,"startPosition":1,"touchArea":" "},{"holdTime":0.0,"isBreak":false,"isEx":false,"isFakeRotate":false,"isForceStar":false,"isHanabi":false,"isSlideBreak":false,"isSlideNoHead":false,"noteContent":"6","noteType":0,"slideStartTime":0.0,"slideTime":0.0,"startPosition":6,"touchArea":" "}],"notesContent":"1/6","rawTextPositionX":9,"rawTextPositionY":1,"time":8.46701040464578},{"currentBpm":194.0,"havePlayed":false,"HSpeed":1.0,"noteList":[{"holdTime":0.0,"isBreak":false,"isEx":false,"isFakeRotate":false,"isForceStar":false,"isHanabi":false,"isSlideBreak":false,"isSlideNoHead":false,"noteContent":"2","noteType":0,"slideStartTime":0.0,"slideTime":0.0,"startPosition":2,"touchArea":" "},{"holdTime":0.0,"isBreak":false,"isEx":false,"isFakeRotate":false,"isForceStar":false,"isHanabi":false,"isSlideBreak":false,"isSlideNoHead":false,"noteContent":"5","noteType":0,"slideStartTime":0.0,"slideTime":0.0,"startPosition":5,"touchArea":" "}],"notesContent":"2/5","rawTextPositionX":13,"rawTextPositionY":1,"time":8.776288755161245},{"currentBpm":194.0,"havePlayed":false,"HSpeed":1.0,"noteList":[{"holdTime":0.6185567010309279,"isBreak":false,"isEx":false,"isFakeRotate":false,"isForceStar":false,"isHanabi":false,"isSlideBreak":false,"isSlideNoHead":false,"noteContent":"3h[2:1]","noteType":2,"slideStartTime":0.0,"slideTime":0.0,"startPosition":3,"touchArea":" "},{"holdTime":0.0,"isBreak":false,"isEx":false,"isFakeRotate":false,"isForceStar":false,"isHanabi":false,"isSlideBreak":false,"isSlideNoHead":false,"noteContent":"4","noteType":0,"slideStartTime":0.0,"slideTime":0.0,"startPosition":4,"touchArea":" "}],"notesContent":"3h[2:1]/4","rawTextPositionX":23,"rawTextPositionY":1,"time":9.08556710567671},{"currentBpm":194.0,"havePlayed":false,"HSpeed":1.0,"noteList":[{"holdTime":0.6185567010309279,"isBreak":false,"isEx":false,"isFakeRotate":false,"isForceStar":false,"isHanabi":false,"isSlideBreak":false,"isSlideNoHead":false,"noteContent":"4h[2:1]","noteType":2,"slideStartTime":0.0,"slideTime":0.0,"startPosition":4,"touchArea":" "}],"notesContent":"4h[2:1]","rawTextPositionX":32,"rawTextPositionY":1,"time":9.704123806707639},{"currentBpm":194.0,"havePlayed":false,"HSpeed":1.0,"noteList":[{"holdTime":0.6185567010309279,"isBreak":false,"isEx":false,"isFakeRotate":false,"isForceStar":false,"isHanabi":false,"isSlideBreak":false,"isSlideNoHead":false,"noteContent":"5h[2:1]","noteType":2,"slideStartTime":0.0,"slideTime":0.0,"startPosition":5,"touchArea":" "}],"notesContent":"5h[2:1]","rawTextPositionX":41,"rawTextPositionY":1,"time":10.322680507738568},{"currentBpm":194.0,"havePlayed":false,"HSpeed":1.0,"noteList":[{"holdTime":0.4639175257731959,"isBreak":false,"isEx":false,"isFakeRotate":false,"isForceStar":false,"isHanabi":false,"isSlideBreak":false,"isSlideNoHead":false,"noteContent":"6h[16:6]","noteType":2,"slideStartTime":0.0,"slideTime":0.0,"startPosition":6,"touchArea":" "}],"notesContent":"6h[16:6]","rawTextPositionX":51,"rawTextPositionY":1,"time":10.941237208769497},{"currentBpm":194.0,"havePlayed":false,"HSpeed":1.0,"noteList":[{"holdTime":0.0,"isBreak":false,"isEx":false,"isFakeRotate":false,"isForceStar":false,"isHanabi":false,"isSlideBreak":false,"isSlideNoHead":false,"noteContent":"6","noteType":0,"slideStartTime":0.0,"slideTime":0.0,"startPosition":6,"touchArea":" "}],"notesContent":"6","rawTextPositionX":54,"rawTextPositionY":1,"time":11.559793909800426},{"currentBpm":194.0,"havePlayed":false,"HSpeed":1.0,"noteList":[{"holdTime":0.0,"isBreak":false,"isEx":false,"isFakeRotate":false,"isForceStar":false,"isHanabi":false,"isSlideBreak":false,"isSlideNoHead":false,"noteContent":"7","noteType":0,"slideStartTime":0.0,"slideTime":0.0,"startPosition":7,"touchArea":" "}],"notesContent":"7","rawTextPositionX":56,"rawTextPositionY":1,"time":11.86907226031589},{"currentBpm":194.0,"havePlayed":false,"HSpeed":1.0,"noteList":[{"holdTime":0.0,"isBreak":false,"isEx":false,"isFakeRotate":false,"isForceStar":false,"isHanabi":false,"isSlideBreak":false,"isSlideNoHead":false,"noteContent":"8","noteType":0,"slideStartTime":0.0,"slideTime":0.0,"startPosition":8,"touchArea":" "}],"notesContent":"8","rawTextPositionX":58,"rawTextPositionY":1,"time":12.178350610831355},{"currentBpm":194.0,"havePlayed":false,"HSpeed":1.0,"noteList":[{"holdTime":0.0,"isBreak":false,"isEx":false,"isFakeRotate":false,"isForceStar":false,"isHanabi":false,"isSlideBreak":false,"isSlideNoHead":false,"noteContent":"1","noteType":0,"slideStartTime":0.0,"slideTime":0.0,"startPosition":1,"touchArea":" "}],"notesContent":"1","rawTextPositionX":60,"rawTextPositionY":1,"time":12.48762896134682},{"currentBpm":194.0,"havePlayed":false,"HSpeed":1.0,"noteList":[{"holdTime":0.0,"isBreak":false,"isEx":false,"isFakeRotate":false,"isForceStar":false,"isHanabi":false,"isSlideBreak":false,"isSlideNoHead":false,"noteContent":"1","noteType":0,"slideStartTime":0.0,"slideTime":0.0,"startPosition":1,"touchArea":" "},{"holdTime":0.0,"isBreak":false,"isEx":false,"isFakeRotate":false,"isForceStar":false,"isHanabi":false,"isSlideBreak":false,"isSlideNoHead":false,"noteContent":"B5","noteType":3,"slideStartTime":0.0,"slideTime":0.0,"startPosition":5,"touchArea":"B"}],"notesContent":"1/B5","rawTextPositionX":8,"rawTextPositionY":2,"time":12.796907311862284},{"currentBpm":194.0,"havePlayed":false,"HSpeed":1.0,"noteList":[{"holdTime":0.0,"isBreak":false,"isEx":false,"isFakeRotate":false,"isForceStar":false,"isHanabi":false,"isSlideBreak":false,"isSlideNoHead":false,"noteContent":"2","noteType":0,"slideStartTime":0.0,"slideTime":0.0,"startPosition":2,"touchArea":" "},{"holdTime":0.0,"isBreak":false,"isEx":false,"isFakeRotate":false,"isForceStar":false,"isHanabi":false,"isSlideBreak":false,"isSlideNoHead":false,"noteContent":"B6","noteType":3,"slideStartTime":0.0,"slideTime":0.0,"startPosition":6,"touchArea":"B"}],"notesContent":"2/B6","rawTextPositionX":13,"rawTextPositionY":2,"time":13.106185662377749},{"currentBpm":194.0,"havePlayed":false,"HSpeed":1.0,"noteList":[{"holdTime":0.0,"isBreak":false,"isEx":false,"isFakeRotate":false,"isForceStar":false,"isHanabi":false,"isSlideBreak":false,"isSlideNoHead":false,"noteContent":"3","noteType":0,"slideStartTime":0.0,"slideTime":0.0,"startPosition":3,"touchArea":" "},{"holdTime":0.0,"isBreak":false,"isEx":false,"isFakeRotate":false,"isForceStar":false,"isHanabi":false,"isSlideBreak":false,"isSlideNoHead":false,"noteContent":"B7","noteType":3,"slideStartTime":0.0,"slideTime":0.0,"startPosition":7,"touchArea":"B"}],"notesContent":"3/B7","rawTextPositionX":18,"rawTextPositionY":2,"time":13.415464012893214},{"currentBpm":194.0,"havePlayed":false,"HSpeed":1.0,"noteList":[{"holdTime":0.0,"isBreak":false,"isEx":false,"isFakeRotate":false,"isForceStar":false,"isHanabi":false,"isSlideBreak":false,"isSlideNoHead":false,"noteContent":"4","noteType":0,"slideStartTime":0.0,"slideTime":0.0,"startPosition":4,"touchArea":" "},{"holdTime":0.0,"isBreak":false,"isEx":false,"isFakeRotate":false,"isForceStar":false,"isHanabi":false,"isSlideBreak":false,"isSlideNoHead":false,"noteContent":"B8","noteType":3,"slideStartTime":0.0,"slideTime":0.0,"startPosition":8,"touchArea":"B"}],"notesContent":"4/B8","rawTextPositionX":23,"rawTextPositionY":2,"time":13.724742363408678},{"currentBpm":194.0,"havePlayed":false,"HSpeed":1.0,"noteList":[{"holdTime":0.0,"isBreak":false,"isEx":false,"isFakeRotate":false,"isForceStar":false,"isHanabi":false,"isSlideBreak":false,"isSlideNoHead":false,"noteContent":"5","noteType":0,"slideStartTime":0.0,"slideTime":0.0,"startPosition":5,"touchArea":" "},{"holdTime":0.0,"isBreak":false,"isEx":false,"isFakeRotate":false,"isForceStar":false,"isHanabi":false,"isSlideBreak":false,"isSlideNoHead":false,"noteContent":"B1","noteType":3,"slideStartTime":0.0,"slideTime":0.0,"startPosition":1,"touchArea":"B"}],"notesContent":"5/B1","rawTextPositionX":28,"rawTextPositionY":2,"time":14.034020713924143},{"currentBpm":194.0,"havePlayed":false,"HSpeed":1.0,"noteList":[{"holdTime":0.0,"isBreak":false,"isEx":false,"isFakeRotate":false,"isForceStar":false,"isHanabi":false,"isSlideBreak":false,"isSlideNoHead":false,"noteContent":"6","noteType":0,"slideStartTime":0.0,"slideTime":0.0,"startPosition":6,"touchArea":" "},{"holdTime":0.0,"isBreak":false,"isEx":false,"isFakeRotate":false,"isForceStar":false,"isHanabi":false,"isSlideBreak":false,"isSlideNoHead":false,"noteContent":"B2","noteType":3,"slideStartTime":0.0,"slideTime":0.0,"startPosition":2,"touchArea":"B"}],"notesContent":"6/B2","rawTextPositionX":33,"rawTextPositionY":2,"time":14.343299064439607},{"currentBpm":194.0,"havePlayed":false,"HSpeed":1.0,"noteList":[{"holdTime":0.0,"isBreak":false,"isEx":false,"isFakeRotate":false,"isForceStar":false,"isHanabi":false,"isSlideBreak":false,"isSlideNoHead":false,"noteContent":"7","noteType":0,"slideStartTime":0.0,"slideTime":0.0,"startPosition":7,"touchArea":" "},{"holdTime":0.0,"isBreak":false,"isEx":false,"isFakeRotate":false,"isForceStar":false,"isHanabi":false,"isSlideBreak":false,"isSlideNoHead":false,"noteContent":"B3","noteType":3,"slideStartTime":0.0,"slideTime":0.0,"startPosition":3,"touchArea":"B"}],"notesContent":"7/B3","rawTextPositionX":38,"rawTextPositionY":2,"time":14.652577414955072},{"currentBpm":194.0,"havePlayed":false,"HSpeed":1.0,"noteList":[{"holdTime":0.0,"isBreak":false,"isEx":false,"isFakeRotate":false,"isForceStar":false,"isHanabi":false,"isSlideBreak":false,"isSlideNoHead":false,"noteContent":"8","noteType":0,"slideStartTime":0.0,"slideTime":0.0,"startPosition":8,"touchArea":" "},{"holdTime":0.0,"isBreak":false,"isEx":false,"isFakeRotate":false,"isForceStar":false,"isHanabi":false,"isSlideBreak":false,"isSlideNoHead":false,"noteContent":"B4","noteType":3,"slideStartTime":0.0,"slideTime":0.0,"startPosition":4,"touchArea":"B"}],"notesContent":"8/B4","rawTextPositionX":43,"rawTextPositionY":2,"time":14.961855765470537},{"currentBpm":194.0,"havePlayed":false,"HSpeed":1.0,"noteList":[{"holdTime":0.0,"isBreak":false,"isEx":false,"isFakeRotate":false,"isForceStar":false,"isHanabi":false,"isSlideBreak":false,"isSlideNoHead":false,"noteContent":"1","noteType":0,"slideStartTime":0.0,"slideTime":0.0,"startPosition":1,"touchArea":" "},{"holdTime":0.0,"isBreak":false,"isEx":false,"isFakeRotate":false,"isForceStar":false,"isHanabi":false,"isSlideBreak":false,"isSlideNoHead":false,"noteContent":"2","noteType":0,"slideStartTime":0.0,"slideTime":0.0,"startPosition":2,"touchArea":" "}],"notesContent":"1/2","rawTextPositionX":47,"rawTextPositionY":2,"time":15.271134115986001},{"currentBpm":194.0,"havePlayed":false,"HSpeed":1.0,"noteList":[{"holdTime":0.0,"isBreak":false,"isEx":false,"isFakeRotate":false,"isForceStar":false,"isHanabi":false,"isSlideBreak":false,"isSlideNoHead":false,"noteContent":"2","noteType":0,"slideStartTime":0.0,"slideTime":0.0,"startPosition":2,"touchArea":" "},{"holdTime":0.0,"isBreak":false,"isEx":false,"isFakeRotate":false,"isForceStar":false,"isHanabi":false,"isSlideBreak":false,"isSlideNoHead":false,"noteContent":"3","noteType":0,"slideStartTime":0.0,"slideTime":0.0,"startPosition":3,"touchArea":" "}],"notesContent":"2/3","rawTextPositionX":51,"rawTextPositionY":2,"time":15.580412466501466},{"currentBpm":194.0,"havePlayed":false,"HSpeed":1.0,"noteList":[{"holdTime":0.0,"isBreak":false,"isEx":false,"isFakeRotate":false,"isForceStar":false,"isHanabi":false,"isSlideBreak":false,"isSlideNoHead":false,"noteContent":"3","noteType":0,"slideStartTime":0.0,"slideTime":0.0,"startPosition":3,"touchArea":" "},{"holdTime":0.0,"isBreak":false,"isEx":false,"isFakeRotate":false,"isForceStar":false,"isHanabi":false,"isSlideBreak":false,"isSlideNoHead":false,"noteContent":"4","noteType":0,"slideStartTime":0.0,"slideTime":0.0,"startPosition":4,"touchArea":" "}],"notesContent":"3/4","rawTextPositionX":55,"rawTextPositionY":2,"time":15.88969081701693},{"currentBpm":194.0,"havePlayed":false,"HSpeed":1.0,"noteList":[{"holdTime":0.0,"isBreak":false,"isEx":false,"isFakeRotate":false,"isForceStar":false,"isHanabi":false,"isSlideBreak":false,"isSlideNoHead":false,"noteContent":"4","noteType":0,"slideStartTime":0.0,"slideTime":0.0,"startPosition":4,"touchArea":" "},{"holdTime":0.0,"isBreak":false,"isEx":false,"isFakeRotate":false,"isForceStar":false,"isHanabi":false,"isSlideBreak":false,"isSlideNoHead":false,"noteContent":"5","noteType":0,"slideStartTime":0.0,"slideTime":0.0,"startPosition":5,"touchArea":" "}],"notesContent":"4/5","rawTextPositionX":59,"rawTextPositionY":2,"time":16.198969167532393},{"currentBpm":194.0,"havePlayed":false,"HSpeed":1.0,"noteList":[{"holdTime":0.0,"isBreak":false,"isEx":false,"isFakeRotate":false,"isForceStar":false,"isHanabi":false,"isSlideBreak":false,"isSlideNoHead":false,"noteContent":"5","noteType":0,"slideStartTime":0.0,"slideTime":0.0,"startPosition":5,"touchArea":" "},{"holdTime":0.0,"isBreak":false,"isEx":false,"isFakeRotate":false,"isForceStar":false,"isHanabi":false,"isSlideBreak":false,"isSlideNoHead":false,"noteContent":"6","noteType":0,"slideStartTime":0.0,"slideTime":0.0,"startPosition":6,"touchArea":" "}],"notesContent":"5/6","rawTextPositionX":63,"rawTextPositionY":2,"time":16.508247518047856},{"currentBpm":194.0,"havePlayed":false,"HSpeed":1.0,"noteList":[{"holdTime":0.0,"isBreak":false,"isEx":false,"isFakeRotate":false,"isForceStar":false,"isHanabi":false,"isSlideBreak":false,"isSlideNoHead":false,"noteContent":"6","noteType":0,"slideStartTime":0.0,"slideTime":0.0,"startPosition":6,"touchArea":" "},{"holdTime":0.0,"isBreak":false,"isEx":false,"isFakeRotate":false,"isForceStar":false,"isHanabi":false,"isSlideBreak":false,"isSlideNoHead":false,"noteContent":"7","noteType":0,"slideStartTime":0.0,"slideTime":0.0,"startPosition":7,"touchArea":" "}],"notesContent":"6/7","rawTextPositionX":67,"rawTextPositionY":2,"time":16.81752586856332},{"currentBpm":194.0,"havePlayed":false,"HSpeed":1.0,"noteList":[{"holdTime":0.0,"isBreak":false,"isEx":false,"isFakeRotate":false,"isForceStar":false,"isHanabi":false,"isSlideBreak":false,"isSlideNoHead":false,"noteContent":"7","noteType":0,"slideStartTime":0.0,"slideTime":0.0,"startPosition":7,"touchArea":" "},{"holdTime":0.0,"isBreak":false,"isEx":false,"isFakeRotate":false,"isForceStar":false,"isHanabi":false,"isSlideBreak":false,"isSlideNoHead":false,"noteContent":"8","noteType":0,"slideStartTime":0.0,"slideTime":0.0,"startPosition":8,"touchArea":" "}],"notesContent":"7/8","rawTextPositionX":71,"rawTextPositionY":2,"time":17.12680421907878},{"currentBpm":194.0,"havePlayed":false,"HSpeed":1.0,"noteList":[{"holdTime":0.0,"isBreak":false,"isEx":false,"isFakeRotate":false,"isForceStar":false,"isHanabi":false,"isSlideBreak":false,"isSlideNoHead":false,"noteContent":"1","noteType":0,"slideStartTime":0.0,"slideTime":0.0,"startPosition":1,"touchArea":" "},{"holdTime":0.0,"isBreak":false,"isEx":false,"isFakeRotate":false,"isForceStar":false,"isHanabi":false,"isSlideBreak":false,"isSlideNoHead":false,"noteContent":"8","noteType":0,"slideStartTime":0.0,"slideTime":0.0,"startPosition":8,"touchArea":" "}],"notesContent":"1/8","rawTextPositionX":75,"rawTextPositionY":2,"time":17.436082569594245},{"currentBpm":194.0,"havePlayed":false,"HSpeed":1.0,"noteList":[{"holdTime":0.0,"isBreak":false,"isEx":false,"isFakeRotate":false,"isForceStar":false,"isHanabi":false,"isSlideBreak":false,"isSlideNoHead":false,"noteContent":"1","noteType":0,"slideStartTime":0.0,"slideTime":0.0,"startPosition":1,"touchArea":" "},{"holdTime":0.0,"isBreak":false,"isEx":false,"isFakeRotate":false,"isForceStar":false,"isHanabi":false,"isSlideBreak":false,"isSlideNoHead":false,"noteContent":"C","noteType":3,"slideStartTime":0.0,"slideTime":0.0,"startPosition":8,"touchArea":"C"}],"notesContent":"1/C","rawTextPositionX":7,"rawTextPositionY":3,"time":17.745360920109707},{"currentBpm":194.0,"havePlayed":false,"HSpeed":1.0,"noteList":[{"holdTime":0.0,"isBreak":false,"isEx":false,"isFakeRotate":false,"isForceStar":false,"isHanabi":false,"isSlideBreak":false,"isSlideNoHead":false,"noteContent":"1","noteType":0,"slideStartTime":0.0,"slideTime":0.0,"startPosition":1,"touchArea":" "}],"notesContent":"1","rawTextPositionX":9,"rawTextPositionY":3,"time":17.90000009536744},{"currentBpm":194.0,"havePlayed":false,"HSpeed":1.0,"noteList":[{"holdTime":0.0,"isBreak":false,"isEx":false,"isFakeRotate":false,"isForceStar":false,"isHanabi":false,"isSlideBreak":false,"isSlideNoHead":false,"noteContent":"1","noteType":0,"slideStartTime":0.0,"slideTime":0.0,"startPosition":1,"touchArea":" "},{"holdTime":0.0,"isBreak":false,"isEx":false,"isFakeRotate":false,"isForceStar":false,"isHanabi":false,"isSlideBreak":false,"isSlideNoHead":false,"noteContent":"C","noteType":3,"slideStartTime":0.0,"slideTime":0.0,"startPosition":8,"touchArea":"C"}],"notesContent":"1/C","rawTextPositionX":13,"rawTextPositionY":3,"time":18.05463927062517},{"currentBpm":194.0,"havePlayed":false,"HSpeed":1.0,"noteList":[{"holdTime":0.0,"isBreak":false,"isEx":false,"isFakeRotate":false,"isForceStar":false,"isHanabi":false,"isSlideBreak":false,"isSlideNoHead":false,"noteContent":"1","noteType":0,"slideStartTime":0.0,"slideTime":0.0,"startPosition":1,"touchArea":" "}],"notesContent":"1","rawTextPositionX":15,"rawTextPositionY":3,"time":18.2092784458829},{"currentBpm":194.0,"havePlayed":false,"HSpeed":1.0,"noteList":[{"holdTime":0.0,"isBreak":false,"isEx":false,"isFakeRotate":false,"isForceStar":false,"isHanabi":false,"isSlideBreak":false,"isSlideNoHead":false,"noteContent":"2","noteType":0,"slideStartTime":0.0,"slideTime":0.0,"startPosition":2,"touchArea":" "},{"holdTime":0.0,"isBreak":false,"isEx":false,"isFakeRotate":false,"isForceStar":false,"isHanabi":false,"isSlideBreak":false,"isSlideNoHead":false,"noteContent":"C","noteType":3,"slideStartTime":0.0,"slideTime":0.0,"startPosition":8,"touchArea":"C"}],"notesContent":"2/C","rawTextPositionX":19,"rawTextPositionY":3,"time":18.363917621140633},{"currentBpm":194.0,"havePlayed":false,"HSpeed":1.0,"noteList":[{"holdTime":0.0,"isBreak":false,"isEx":false,"isFakeRotate":false,"isForceStar":false,"isHanabi":false,"isSlideBreak":false,"isSlideNoHead":false,"noteContent":"2","noteType":0,"slideStartTime":0.0,"slideTime":0.0,"startPosition":2,"touchArea":" "}],"notesContent":"2","rawTextPositionX":21,"rawTextPositionY":3,"time":18.518556796398364},{"currentBpm":194.0,"havePlayed":false,"HSpeed":1.0,"noteList":[{"holdTime":0.0,"isBreak":false,"isEx":false,"isFakeRotate":false,"isForceStar":false,"isHanabi":false,"isSlideBreak":false,"isSlideNoHead":false,"noteContent":"2","noteType":0,"slideStartTime":0.0,"slideTime":0.0,"startPosition":2,"touchArea":" "},{"holdTime":0.0,"isBreak":false,"isEx":false,"isFakeRotate":false,"isForceStar":false,"isHanabi":false,"isSlideBreak":false,"isSlideNoHead":false,"noteContent":"C","noteType":3,"slideStartTime":0.0,"slideTime":0.0,"startPosition":8,"touchArea":"C"}],"notesContent":"2/C","rawTextPositionX":25,"rawTextPositionY":3,"time":18.673195971656096},{"currentBpm":194.0,"havePlayed":false,"HSpeed":1.0,"noteList":[{"holdTime":0.0,"isBreak":false,"isEx":false,"isFakeRotate":false,"isForceStar":false,"isHanabi":false,"isSlideBreak":false,"isSlideNoHead":false,"noteContent":"2","noteType":0,"slideStartTime":0.0,"slideTime":0.0,"startPosition":2,"touchArea":" "}],"notesContent":"2","rawTextPositionX":27,"rawTextPositionY":3,"time":18.827835146913827},{"currentBpm":194.0,"havePlayed":false,"HSpeed":1.0,"noteList":[{"holdTime":0.0,"isBreak":false,"isEx":false,"isFakeRotate":false,"isForceStar":false,"isHanabi":false,"isSlideBreak":false,"isSlideNoHead":false,"noteContent":"5","noteType":0,"slideStartTime":0.0,"slideTime":0.0,"startPosition":5,"touchArea":" "},{"holdTime":0.0,"isBreak":false,"isEx":false,"isFakeRotate":false,"isForceStar":false,"isHanabi":false,"isSlideBreak":false,"isSlideNoHead":false,"noteContent":"C","noteType":3,"slideStartTime":0.0,"slideTime":0.0,"startPosition":8,"touchArea":"C"}],"notesContent":"5/C","rawTextPositionX":31,"rawTextPositionY":3,"time":18.98247432217156},{"currentBpm":194.0,"havePlayed":false,"HSpeed":1.0,"noteList":[{"holdTime":0.0,"isBreak":false,"isEx":false,"isFakeRotate":false,"isForceStar":false,"isHanabi":false,"isSlideBreak":false,"isSlideNoHead":false,"noteContent":"5","noteType":0,"slideStartTime":0.0,"slideTime":0.0,"startPosition":5,"touchArea":" "}],"notesContent":"5","rawTextPositionX":33,"rawTextPositionY":3,"time":19.13711349742929},{"currentBpm":194.0,"havePlayed":false,"HSpeed":1.0,"noteList":[{"holdTime":0.0,"isBreak":false,"isEx":false,"isFakeRotate":false,"isForceStar":false,"isHanabi":false,"isSlideBreak":false,"isSlideNoHead":false,"noteContent":"5","noteType":0,"slideStartTime":0.0,"slideTime":0.0,"startPosition":5,"touchArea":" "},{"holdTime":0.0,"isBreak":false,"isEx":false,"isFakeRotate":false,"isForceStar":false,"isHanabi":false,"isSlideBreak":false,"isSlideNoHead":false,"noteContent":"C","noteType":3,"slideStartTime":0.0,"slideTime":0.0,"startPosition":8,"touchArea":"C"}],"notesContent":"5/C","rawTextPositionX":37,"rawTextPositionY":3,"time":19.29175267268702},{"currentBpm":194.0,"havePlayed":false,"HSpeed":1.0,"noteList":[{"holdTime":0.0,"isBreak":false,"isEx":false,"isFakeRotate":false,"isForceStar":false,"isHanabi":false,"isSlideBreak":false,"isSlideNoHead":false,"noteContent":"5","noteType":0,"slideStartTime":0.0,"slideTime":0.0,"startPosition":5,"touchArea":" "}],"notesContent":"5","rawTextPositionX":39,"rawTextPositionY":3,"time":19.446391847944753},{"currentBpm":194.0,"havePlayed":false,"HSpeed":1.0,"noteList":[{"holdTime":0.0,"isBreak":false,"isEx":false,"isFakeRotate":false,"isForceStar":false,"isHanabi":false,"isSlideBreak":false,"isSlideNoHead":false,"noteContent":"6","noteType":0,"slideStartTime":0.0,"slideTime":0.0,"startPosition":6,"touchArea":" "},{"holdTime":0.0,"isBreak":false,"isEx":false,"isFakeRotate":false,"isForceStar":false,"isHanabi":false,"isSlideBreak":false,"isSlideNoHead":false,"noteContent":"C","noteType":3,"slideStartTime":0.0,"slideTime":0.0,"startPosition":8,"touchArea":"C"}],"notesContent":"6/C","rawTextPositionX":43,"rawTextPositionY":3,"time":19.601031023202484},{"currentBpm":194.0,"havePlayed":false,"HSpeed":1.0,"noteList":[{"holdTime":0.0,"isBreak":false,"isEx":false,"isFakeRotate":false,"isForceStar":false,"isHanabi":false,"isSlideBreak":false,"isSlideNoHead":false,"noteContent":"6","noteType":0,"slideStartTime":0.0,"slideTime":0.0,"startPosition":6,"touchArea":" "}],"notesContent":"6","rawTextPositionX":45,"rawTextPositionY":3,"time":19.755670198460216},{"currentBpm":194.0,"havePlayed":false,"HSpeed":1.0,"noteList":[{"holdTime":0.0,"isBreak":false,"isEx":false,"isFakeRotate":false,"isForceStar":false,"isHanabi":false,"isSlideBreak":false,"isSlideNoHead":false,"noteContent":"6","noteType":0,"slideStartTime":0.0,"slideTime":0.0,"startPosition":6,"touchArea":" "},{"holdTime":0.0,"isBreak":false,"isEx":false,"isFakeRotate":false,"isForceStar":false,"isHanabi":false,"isSlideBreak":false,"isSlideNoHead":false,"noteContent":"C","noteType":3,"slideStartTime":0.0,"slideTime":0.0,"startPosition":8,"touchArea":"C"}],"notesContent":"6/C","rawTextPositionX":49,"rawTextPositionY":3,"time":19.910309373717947},{"currentBpm":194.0,"havePlayed":false,"HSpeed":1.0,"noteList":[{"holdTime":0.0,"isBreak":false,"isEx":false,"isFakeRotate":false,"isForceStar":false,"isHanabi":false,"isSlideBreak":false,"isSlideNoHead":false,"noteContent":"6","noteType":0,"slideStartTime":0.0,"slideTime":0.0,"startPosition":6,"touchArea":" "}],"notesContent":"6","rawTextPositionX":51,"rawTextPositionY":3,"time":20.06494854897568},{"currentBpm":194.0,"havePlayed":false,"HSpeed":1.0,"noteList":[{"holdTime":0.0,"isBreak":false,"isEx":false,"isFakeRotate":false,"isForceStar":false,"isHanabi":false,"isSlideBreak":false,"isSlideNoHead":false,"noteContent":"7","noteType":0,"slideStartTime":0.0,"slideTime":0.0,"startPosition":7,"touchArea":" "}],"notesContent":"7","rawTextPositionX":6,"rawTextPositionY":4,"time":20.21958772423341},{"currentBpm":194.0,"havePlayed":false,"HSpeed":1.0,"noteList":[{"holdTime":0.0,"isBreak":false,"isEx":false,"isFakeRotate":false,"isForceStar":false,"isHanabi":false,"isSlideBreak":false,"isSlideNoHead":false,"noteContent":"8","noteType":0,"slideStartTime":0.0,"slideTime":0.0,"startPosition":8,"touchArea":" "}],"notesContent":"8","rawTextPositionX":8,"rawTextPositionY":4,"time":20.296907311862277},{"currentBpm":194.0,"havePlayed":false,"HSpeed":1.0,"noteList":[{"holdTime":0.0,"isBreak":false,"isEx":false,"isFakeRotate":false,"isForceStar":false,"isHanabi":false,"isSlideBreak":false,"isSlideNoHead":false,"noteContent":"1","noteType":0,"slideStartTime":0.0,"slideTime":0.0,"startPosition":1,"touchArea":" "}],"notesContent":"1","rawTextPositionX":10,"rawTextPositionY":4,"time":20.374226899491145},{"currentBpm":194.0,"havePlayed":false,"HSpeed":1.0,"noteList":[{"holdTime":0.0,"isBreak":false,"isEx":false,"isFakeRotate":false,"isForceStar":false,"isHanabi":false,"isSlideBreak":false,"isSlideNoHead":false,"noteContent":"2","noteType":0,"slideStartTime":0.0,"slideTime":0.0,"startPosition":2,"touchArea":" "}],"notesContent":"2","rawTextPositionX":12,"rawTextPositionY":4,"time":20.451546487120012},{"currentBpm":194.0,"havePlayed":false,"HSpeed":1.0,"noteList":[{"holdTime":0.0,"isBreak":false,"isEx":false,"isFakeRotate":false,"isForceStar":false,"isHanabi":false,"isSlideBreak":false,"isSlideNoHead":false,"noteContent":"3","noteType":0,"slideStartTime":0.0,"slideTime":0.0,"startPosition":3,"touchArea":" "}],"notesContent":"3","rawTextPositionX":14,"rawTextPositionY":4,"time":20.52886607474888},{"currentBpm":194.0,"havePlayed":false,"HSpeed":1.0,"noteList":[{"holdTime":0.0,"isBreak":false,"isEx":false,"isFakeRotate":false,"isForceStar":false,"isHanabi":false,"isSlideBreak":false,"isSlideNoHead":false,"noteContent":"4","noteType":0,"slideStartTime":0.0,"slideTime":0.0,"startPosition":4,"touchArea":" "}],"notesContent":"4","rawTextPositionX":16,"rawTextPositionY":4,"time":20.606185662377747},{"currentBpm":194.0,"havePlayed":false,"HSpeed":1.0,"noteList":[{"holdTime":0.0,"isBreak":false,"isEx":false,"isFakeRotate":false,"isForceStar":false,"isHanabi":false,"isSlideBreak":false,"isSlideNoHead":false,"noteContent":"5","noteType":0,"slideStartTime":0.0,"slideTime":0.0,"startPosition":5,"touchArea":" "}],"notesContent":"5","rawTextPositionX":18,"rawTextPositionY":4,"time":20.683505250006615},{"currentBpm":194.0,"havePlayed":false,"HSpeed":1.0,"noteList":[{"holdTime":0.0,"isBreak":false,"isEx":false,"isFakeRotate":false,"isForceStar":false,"isHanabi":false,"isSlideBreak":false,"isSlideNoHead":false,"noteContent":"6","noteType":0,"slideStartTime":0.0,"slideTime":0.0,"startPosition":6,"touchArea":" "}],"notesContent":"6","rawTextPositionX":20,"rawTextPositionY":4,"time":20.760824837635482},{"currentBpm":194.0,"havePlayed":false,"HSpeed":1.0,"noteList":[{"holdTime":0.0,"isBreak":false,"isEx":false,"isFakeRotate":false,"isForceStar":false,"isHanabi":false,"isSlideBreak":false,"isSlideNoHead":false,"noteContent":"7","noteType":0,"slideStartTime":0.0,"slideTime":0.0,"startPosition":7,"touchArea":" "}],"notesContent":"7","rawTextPositionX":22,"rawTextPositionY":4,"time":20.83814442526435},{"currentBpm":194.0,"havePlayed":false,"HSpeed":1.0,"noteList":[{"holdTime":0.0,"isBreak":false,"isEx":false,"isFakeRotate":false,"isForceStar":false,"isHanabi":false,"isSlideBreak":false,"isSlideNoHead":false,"noteContent":"8","noteType":0,"slideStartTime":0.0,"slideTime":0.0,"startPosition":8,"touchArea":" "}],"notesContent":"8","rawTextPositionX":24,"rawTextPositionY":4,"time":20.915464012893217},{"currentBpm":194.0,"havePlayed":false,"HSpeed":1.0,"noteList":[{"holdTime":0.0,"isBreak":false,"isEx":false,"isFakeRotate":false,"isForceStar":false,"isHanabi":false,"isSlideBreak":false,"isSlideNoHead":false,"noteContent":"1","noteType":0,"slideStartTime":0.0,"slideTime":0.0,"startPosition":1,"touchArea":" "}],"notesContent":"1","rawTextPositionX":26,"rawTextPositionY":4,"time":20.992783600522085},{"currentBpm":194.0,"havePlayed":false,"HSpeed":1.0,"noteList":[{"holdTime":0.0,"isBreak":false,"isEx":false,"isFakeRotate":false,"isForceStar":false,"isHanabi":false,"isSlideBreak":false,"isSlideNoHead":false,"noteContent":"2","noteType":0,"slideStartTime":0.0,"slideTime":0.0,"startPosition":2,"touchArea":" "}],"notesContent":"2","rawTextPositionX":28,"rawTextPositionY":4,"time":21.070103188150952},{"currentBpm":194.0,"havePlayed":false,"HSpeed":1.0,"noteList":[{"holdTime":0.0,"isBreak":false,"isEx":false,"isFakeRotate":false,"isForceStar":false,"isHanabi":false,"isSlideBreak":false,"isSlideNoHead":false,"noteContent":"3","noteType":0,"slideStartTime":0.0,"slideTime":0.0,"startPosition":3,"touchArea":" "}],"notesContent":"3","rawTextPositionX":30,"rawTextPositionY":4,"time":21.14742277577982},{"currentBpm":194.0,"havePlayed":false,"HSpeed":1.0,"noteList":[{"holdTime":0.0,"isBreak":false,"isEx":false,"isFakeRotate":false,"isForceStar":false,"isHanabi":false,"isSlideBreak":false,"isSlideNoHead":false,"noteContent":"4","noteType":0,"slideStartTime":0.0,"slideTime":0.0,"startPosition":4,"touchArea":" "}],"notesContent":"4","rawTextPositionX":32,"rawTextPositionY":4,"time":21.224742363408687},{"currentBpm":194.0,"havePlayed":false,"HSpeed":1.0,"noteList":[{"holdTime":0.0,"isBreak":false,"isEx":false,"isFakeRotate":false,"isForceStar":false,"isHanabi":false,"isSlideBreak":false,"isSlideNoHead":false,"noteContent":"5","noteType":0,"slideStartTime":0.0,"slideTime":0.0,"startPosition":5,"touchArea":" "}],"notesContent":"5","rawTextPositionX":34,"rawTextPositionY":4,"time":21.302061951037555},{"currentBpm":194.0,"havePlayed":false,"HSpeed":1.0,"noteList":[{"holdTime":0.0,"isBreak":false,"isEx":false,"isFakeRotate":false,"isForceStar":false,"isHanabi":false,"isSlideBreak":false,"isSlideNoHead":false,"noteContent":"6","noteType":0,"slideStartTime":0.0,"slideTime":0.0,"startPosition":6,"touchArea":" "}],"notesContent":"6","rawTextPositionX":36,"rawTextPositionY":4,"time":21.379381538666422},{"currentBpm":194.0,"havePlayed":false,"HSpeed":1.0,"noteList":[{"holdTime":0.0,"isBreak":false,"isEx":false,"isFakeRotate":false,"isForceStar":false,"isHanabi":false,"isSlideBreak":false,"isSlideNoHead":false,"noteContent":"7","noteType":0,"slideStartTime":0.0,"slideTime":0.0,"startPosition":7,"touchArea":" "}],"notesContent":"7","rawTextPositionX":6,"rawTextPositionY":5,"time":21.45670112629529},{"currentBpm":194.0,"havePlayed":false,"HSpeed":1.0,"noteList":[{"holdTime":0.0,"isBreak":false,"isEx":false,"isFakeRotate":false,"isForceStar":false,"isHanabi":false,"isSlideBreak":false,"isSlideNoHead":false,"noteContent":"8","noteType":0,"slideStartTime":0.0,"slideTime":0.0,"startPosition":8,"touchArea":" "}],"notesContent":"8","rawTextPositionX":11,"rawTextPositionY":5,"time":21.76597947681076},{"currentBpm":194.0,"havePlayed":false,"HSpeed":1.0,"noteList":[{"holdTime":0.0,"isBreak":false,"isEx":false,"isFakeRotate":false,"isForceStar":false,"isHanabi":false,"isSlideBreak":false,"isSlideNoHead":false,"noteContent":"1","noteType":0,"slideStartTime":0.0,"slideTime":0.0,"startPosition":1,"touchArea":" "}],"notesContent":"1","rawTextPositionX":15,"rawTextPositionY":5,"time":21.997938239697362},{"currentBpm":194.0,"havePlayed":false,"HSpeed":1.0,"noteList":[{"holdTime":0.0,"isBreak":false,"isEx":false,"isFakeRotate":false,"isForceStar":false,"isHanabi":false,"isSlideBreak":false,"isSlideNoHead":false,"noteContent":"1w5[97#32:1]","noteType":1,"slideStartTime":22.69381452835716,"slideTime":0.07731958762886598,"startPosition":1,"touchArea":" "}],"notesContent":"1w5[97#32:1]","rawTextPositionX":31,"rawTextPositionY":5,"time":22.07525782732623}],"title":"ネバーランド"}